WebLamp/__init__.py
WebLamp/lamp.py
WebLamp/utils.py
WebLamp-0.3.0.dist-info/LICENSE
WebLamp-0.3.0.dist-info/METADATA
WebLamp-0.3.0.dist-info/WHEEL
WebLamp-0.3.0.dist-info/top_level.txt
WebLamp-0.3.0.dist-info/RECORD
