Metadata-Version: 2.1
Name: WebLamp
Version: 0.3.0
Summary: A socket webserver made in python!
Home-page: https://github.com/coverosu/lamp
Author: coverosu
Author-email: coverosu@gmail.com
License: UNKNOWN
Platform: UNKNOWN
Classifier: Programming Language :: Python :: 3
Classifier: License :: OSI Approved :: MIT License
Classifier: Operating System :: OS Independent
Requires-Python: >=3.8
